{
  "paper_id": "1207.4747",
  "title": "Stochastic Block-Coordinate Frank-Wolfe Optimization for Structural SVMs",
  "bib_entries": {
    "BIBREF0": {
      "title": "Fast Stochastic Frank-Wolfe Algorithms for Nonlinear SVMs.",
      "authors": [
        "Hua Ouyang",
        "Alexander G. Gray"
      ],
      "year": 2010,
      "venue": "SIAM International Conference on Data Mining",
      "link": ""
    },
    "BIBREF1": {
      "title": "Coresets for polytope distance",
      "authors": [
        "Bernd Gärtner",
        "Martin Jaggi"
      ],
      "year": 2009,
      "venue": "Symposium on Computational Geometry",
      "link": "https://api.semanticscholar.org/graph/v1/paper/10.1145/1542362.1542370"
    },
    "BIBREF2": {
      "title": "A scalable modular convex solver for regularized risk minimization",
      "authors": [
        "Choon Hui Teo",
        "Alex Smola",
        "S. V.N. Vishwanathan",
        "Quoc Viet Le"
      ],
      "year": 2007,
      "venue": "Knowledge Discovery and Data Mining",
      "link": "https://api.semanticscholar.org/graph/v1/paper/10.1145/1281192.1281270"
    },
    "BIBREF3": {
      "title": "Cutting-plane training of structural SVMs",
      "authors": [
        "Thorsten Joachims",
        "Thomas Finley",
        "Chun-Nam John Yu"
      ],
      "year": 2009,
      "venue": "Machine Learning",
      "link": "https://api.semanticscholar.org/graph/v1/paper/10.1007/s10994-009-5108-8"
    },
    "BIBREF4": {
      "title": "Learning with Submodular Functions: A Convex Optimization Perspective",
      "authors": [
        "Francis Bach"
      ],
      "year": 2013,
      "venue": "",
      "link": ""
    },
    "BIBREF5": {
      "title": "Training structural SVMs when exact inference is intractable",
      "authors": [
        "Thomas Finley",
        "Thorsten Joachims"
      ],
      "year": 2008,
      "venue": "International Conference on Machine Learning",
      "link": "https://api.semanticscholar.org/graph/v1/paper/10.1145/1390156.1390195"
    },
    "BIBREF6": {
      "title": "Efficiency of Coordinate Descent Methods on Huge-Scale Optimization Problems",
      "authors": [
        "Yurii E. Nesterov"
      ],
      "year": 2012,
      "venue": "Siam Journal on Optimization",
      "link": "https://api.semanticscholar.org/graph/v1/paper/10.1137/100802001"
    },
    "BIBREF7": {
      "title": "Learning structured prediction models: a large margin approach",
      "authors": [
        "Ben Taskar",
        "Vassil Chatalbashev",
        "Daphne Koller",
        "Carlos Guestrin"
      ],
      "year": 2005,
      "venue": "International Conference on Machine Learning",
      "link": "https://api.semanticscholar.org/graph/v1/paper/10.1145/1102351.1102464"
    },
    "BIBREF8": {
      "title": "Introduction to the CoNLL-2000 shared task: chunking",
      "authors": [
        "Erik F. Tjong Kim Sang",
        "Sabine Buchholz"
      ],
      "year": 2000,
      "venue": "Conference on Computational Natural Language Learning",
      "link": "https://api.semanticscholar.org/graph/v1/paper/10.3115/1117601.1117631"
    },
    "BIBREF9": {
      "title": "Structured Prediction, Dual Extragradient and Bregman Projections",
      "authors": [
        "Ben Taskar",
        "Simon Lacoste-Julien",
        "Michael I. Jordan"
      ],
      "year": 2006,
      "venue": "Journal of Machine Learning Research",
      "link": ""
    },
    "BIBREF10": {
      "title": "Max-Margin Markov Networks",
      "authors": [
        "Ben Taskar",
        "Carlos Guestrin",
        "Daphne Koller"
      ],
      "year": 2003,
      "venue": "Neural Information Processing Systems",
      "link": ""
    },
    "BIBREF11": {
      "title": "Large Margin Methods for Structured and Interdependent Output Variables",
      "authors": [
        "Ioannis Tsochantaridis",
        "Thorsten Joachims",
        "Thomas Hofmann",
        "Yasemin Altun"
      ],
      "year": 2005,
      "venue": "Journal of Machine Learning Research",
      "link": ""
    },
    "BIBREF12": {
      "title": "Bundle Methods for Regularized Risk Minimization",
      "authors": [
        "Choon Hui Teo",
        "S.V.N. Vishwanthan",
        "Alex J. Smola",
        "Quoc V. Le"
      ],
      "year": 2010,
      "venue": "Journal of Machine Learning Research",
      "link": ""
    },
    "BIBREF13": {
      "title": "Pegasos: Primal Estimated sub-GrAdient SOlver for SVM",
      "authors": [
        "Shai Shalev-Shwartz",
        "Yoram Singer",
        "Nathan Srebro"
      ],
      "year": 2007,
      "venue": "International Conference on Machine Learning",
      "link": "https://api.semanticscholar.org/graph/v1/paper/10.1145/1273496.1273598"
    },
    "BIBREF14": {
      "title": "Exponentiated Gradient Algorithms for Conditional Random Fields and Max-Margin Markov Networks",
      "authors": [
        "Michael Collins",
        "Amir Globerson",
        "Terry Koo",
        "Xavier Carreras",
        "Peter L. Bartlett"
      ],
      "year": 2008,
      "venue": "Journal of Machine Learning Research",
      "link": ""
    },
    "BIBREF15": {
      "title": "Learning Graph Matching",
      "authors": [
        "T.S. Caetano",
        "J.J. McAuley",
        "Li Cheng",
        "Q.V. Le",
        "A.J. Smola"
      ],
      "year": 2009,
      "venue": "IEEE Transactions on Pattern Analysis and Machine Intelligence",
      "link": "https://api.semanticscholar.org/graph/v1/paper/10.1109/TPAMI.2009.28"
    },
    "BIBREF16": {
      "title": "A dual coordinate descent method for large-scale linear SVM",
      "authors": [
        "Cho-Jui Hsieh",
        "Kai-Wei Chang",
        "Chih-Jen Lin",
        "S. Sathiya Keerthi",
        "S. Sundararajan"
      ],
      "year": 2008,
      "venue": "International Conference on Machine Learning",
      "link": "https://api.semanticscholar.org/graph/v1/paper/10.1145/1390156.1390208"
    },
    "BIBREF17": {
      "title": "Accelerated training of max-margin Markov networks with kernels",
      "authors": [
        "Xinhua Zhang",
        "Ankan Saha",
        "S. V. N. Vishwanathan"
      ],
      "year": 2014,
      "venue": "Theoretical Computer Science",
      "link": "https://api.semanticscholar.org/graph/v1/paper/10.1016/j.tcs.2013.09.026"
    },
    "BIBREF18": {
      "title": "A sequential dual method for structural SVMs",
      "authors": [
        "P Balamurugan",
        "Shirish Shevade",
        "S Sundararajan",
        "Sathiya S Keerthi"
      ],
      "year": 2011,
      "venue": "SIAM International Conference on Data Mining",
      "link": ""
    },
    "BIBREF19": {
      "title": "Coresets, sparse greedy approximation, and the Frank-Wolfe algorithm",
      "authors": [
        "Kenneth L. Clarkson"
      ],
      "year": 2008,
      "venue": "Symposium on Discrete Algorithms",
      "link": ""
    },
    "BIBREF20": {
      "title": "Making Gradient Descent Optimal for Strongly Convex Stochastic Optimization",
      "authors": [
        "Alexander Rakhlin",
        "Ohad Shamir",
        "Karthik Sridharan"
      ],
      "year": 2011,
      "venue": "arXiv: Learning",
      "link": ""
    }
  }
}